gpx_player/__init__.py
gpx_player/clean_gpx.py
gpx_player/gpx_utils.py
gpx_player/main.py
gpx_player/openseamap.py
gpx_player/utils.py
gpx_player/validator.py
gpx_player-0.2.1.dist-info/licenses/LICENSE
schema/gpx_1.0.xsd
schema/gpx_1.1.xsd
tests/__init__.py
tests/test_cleanup.py
tests/test_openseamap.py
tests/test_utils.py
tests/test_validation.py
gpx_player-0.2.1.dist-info/METADATA
gpx_player-0.2.1.dist-info/WHEEL
gpx_player-0.2.1.dist-info/entry_points.txt
gpx_player-0.2.1.dist-info/top_level.txt
gpx_player-0.2.1.dist-info/RECORD
