Metadata-Version: 2.4
Name: gpx-player
Version: 0.2.1
Summary: Visualise & animate GPX race tracks.
Author: Yury Kirienko
License: MIT License
Requires-Python: >=3.8
License-File: LICENSE
Requires-Dist: folium
Requires-Dist: jinja2
Requires-Dist: matplotlib
Requires-Dist: pytz
Requires-Dist: lxml
Requires-Dist: numpy
Requires-Dist: gpxpy
Dynamic: license-file
